multimodal_cci/__init__.py
multimodal_cci/analysis.py
multimodal_cci/integration.py
multimodal_cci/plot_helper.py
multimodal_cci/plotting.py
multimodal_cci/scoring.py
multimodal_cci/tools.py
multimodal_cci-1.2.2.dist-info/.ipynb_checkpoints/PKG-INFO-checkpoint
multimodal_cci-1.2.2.dist-info/.ipynb_checkpoints/SOURCES-checkpoint.txt
multimodal_cci-1.2.2.dist-info/.ipynb_checkpoints/dependency_links-checkpoint.txt
multimodal_cci-1.2.2.dist-info/.ipynb_checkpoints/requires-checkpoint.txt
multimodal_cci-1.2.2.dist-info/.ipynb_checkpoints/top_level-checkpoint.txt
multimodal_cci-1.2.2.dist-info/LICENSE.txt
multimodal_cci-1.2.2.dist-info/METADATA
multimodal_cci-1.2.2.dist-info/WHEEL
multimodal_cci-1.2.2.dist-info/top_level.txt
multimodal_cci-1.2.2.dist-info/RECORD
