Metadata-Version: 2.1
Name: multimodal_cci
Version: 1.2.2
Summary: A Python package for processing multi-modal CCI data
Home-page: https://github.com/BiomedicalMachineLearning/MultimodalCCI
Author: Genomics and Machine Learning lab
Author-email: l.hockey@uq.edu.au
Project-URL: Bug Tracker, https://github.com/BiomedicalMachineLearning/MultimodalCCI/issues
Project-URL: repository, https://github.com/BiomedicalMachineLearning/MultimodalCCI
Classifier: Programming Language :: Python :: 3
Classifier: License :: OSI Approved :: MIT License
Classifier: Operating System :: OS Independent
Requires-Python: >=3.9
License-File: LICENSE.txt
Requires-Dist: numpy >=1.24.0
Requires-Dist: pandas >=2.1.4
Requires-Dist: networkx >=3.2.1
Requires-Dist: matplotlib >=3.8.2
Requires-Dist: scikit-learn >=1.3.0
Requires-Dist: scipy >=1.9.1
Requires-Dist: tqdm >=4.66.1
Requires-Dist: gseapy >=1.1.1
Requires-Dist: scanpy >=1.9.0
Requires-Dist: seaborn >=0.11.2
